{
  "ngDeps": {
    "1": "",
    "3": [
      {
        "1": "package:angular2/core.dart",
        "5": false
      },
      {
        "1": "package:angular2/router.dart",
        "5": false
      },
      {
        "1": "package:moch_personal_site/pages/page1/page1.dart",
        "5": false
      },
      {
        "1": "package:moch_personal_site/pages/page2/page2.dart",
        "5": false
      },
      {
        "1": "package:moch_personal_site/pages/page3/page3.dart",
        "5": false
      }
    ],
    "5": [
      {
        "1": "MainMenuComponent",
        "7": [
          {
            "2": "ROUTER_DIRECTIVES"
          },
          {
            "2": "Page1Component"
          },
          {
            "2": "Page2Component"
          },
          {
            "2": "Page3Component"
          }
        ]
      }
    ],
    "6": "mainMenu.dart"
  },
  "type": {
    "MainMenuComponent": {
      "class": "Directive",
      "isComponent": true,
      "selector": "my-main-menu",
      "exportAs": null,
      "type": {
        "class": "Type",
        "name": "MainMenuComponent",
        "moduleUrl": "asset:moch_personal_site/lib/components/mainMenu/mainMenu.dart",
        "prefix": null,
        "isHost": false,
        "value": null,
        "diDeps": []
      },
      "changeDetection": 6,
      "inputs": {},
      "inputTypes": {},
      "outputs": {},
      "hostListeners": {},
      "hostProperties": {},
      "hostAttributes": {},
      "lifecycleHooks": [],
      "template": {
        "encapsulation": 2,
        "template": "<div>\r\n    <a [routerLink]=\"['Page1']\">תקציר תיק</a>\r\n    <a [routerLink]=\"['Page2']\">חידוש הצהרות</a>\r\n    <a [routerLink]=\"['Page3']\">פניה לועדה</a>\r\n</div>\r\n",
        "templateUrl": "asset:moch_personal_site/lib/components/mainMenu/mainMenu.html",
        "styles": [],
        "styleUrls": [],
        "ngContentSelectors": []
      },
      "providers": [],
      "viewProviders": [],
      "queries": [],
      "viewQueries": []
    }
  },
  "alias": {}
}